sw1dto2d/__init__.py
sw1dto2d/cartesian.py
sw1dto2d/sw1dto2d.py
tests/__init__.py
tests/test_basic_processes.py
tests/test_brahmaputra.py
tests/test_garonne.py
tests/data/brahmaputra/brahmaputra_results.csv
tests/data/brahmaputra/centerline.dbf
tests/data/brahmaputra/centerline.prj
tests/data/brahmaputra/centerline.shp
tests/data/brahmaputra/centerline.shx
tests/data/garonne/Garonne2019_results_selection.csv
tests/data/garonne/__init__.py
tests/data/garonne/centerline.dbf
tests/data/garonne/centerline.prj
tests/data/garonne/centerline.shp
tests/data/garonne/centerline.shx
sw1dto2d-0.0.7.dist-info/LICENSE
sw1dto2d-0.0.7.dist-info/METADATA
sw1dto2d-0.0.7.dist-info/WHEEL
sw1dto2d-0.0.7.dist-info/top_level.txt
sw1dto2d-0.0.7.dist-info/RECORD
